{
  "meta": {
    "releasedOn": "2023.06.27"
  },
  "added": [
    {
      "what": [
        "."
      ],
      "why": [
        "."
      ],
      "refs": [
        "",
        ""
      ]
    },
    {
      "what": [
        "."
      ],
      "why": [
        "."
      ],
      "refs": [
        ""
      ]
    }
  ],
  "changed": [
    {
      "what": [
        "."
      ],
      "why": [
        "."
      ],
      "refs": [
        ""
      ]
    }
  ],
  "fixed": [
    {
      "what": [
        "."
      ],
      "refs": [
        ""
      ]
    }
  ]
}
